w4h/__init__.py
w4h/classify.py
w4h/clean.py
w4h/core.py
w4h/export.py
w4h/layers.py
w4h/mapping.py
w4h/read.py
w4h/visualization.py
w4h/w4h_gui.py
w4h/resources/Dataframe length v number of unique words.png
w4h/resources/base_lithology_terms.csv
w4h/resources/lithology_codes_USGS_GWSI.json
w4h/resources/procesing_diagram.pdf
w4h/resources/procesing_diagram.pptx
w4h/resources/resReadme.md
w4h/resources/resource_home.txt
w4h/resources/temp4wiki.md
w4h/resources/uniqueparameters.xlsx
w4h/resources/sample_data/LocalSample_Bedrock_elev_EStLGrimleyPhillips.tif
w4h/resources/sample_data/downholeDataTypes.json
w4h/resources/sample_data/grid_625_raster.tif
w4h/resources/sample_data/headerDataTypes.json
w4h/resources/sample_data/isws_crs.json
w4h/resources/sample_data/sample_bedrock_elev_grimleyphillips_ESTL.tif
w4h/resources/sample_data/sample_studyArea.zip
w4h/resources/sample_data/sample_surface_bedrock_lidarresampled100ft.tif
w4h/resources/sample_data/sample_well_data.txt
w4h/resources/sample_data/xyzDataTypes.json
w4h/resources/sample_data/DictionaryTerms/DICTIONARY_SearchTerms-Specific_2023-06-27.csv
w4h/resources/sample_data/DictionaryTerms/SearchTerms-Specific_2022-11-16_essCols.csv
w4h/resources/sample_data/DictionaryTerms/SearchTerms-Start.csv
w4h/resources/sample_data/DictionaryTerms/SearchTerms-Wildcard.csv
w4h/resources/sample_data/DictionaryTerms/Stillneed2BeDefined_2023-01-11.csv
w4h/resources/sample_data/LithologyInterpretations/Lithology_Interp_Clay.csv
w4h/resources/sample_data/LithologyInterpretations/Lithology_Interp_FineCoarse.csv
w4h/resources/sample_data/LithologyInterpretations/Lithology_Interp_Gravel.csv
w4h/resources/sample_data/LithologyInterpretations/Lithology_Interp_Sand.csv
w4h/resources/sample_data/LithologyInterpretations/Lithology_Interp_Silt.csv
w4h/resources/sample_data/statewide_sample_data/IL_Statewide_Bedrock_Elev_2023_ft_625ft_Lambert_GridAlign.tif
w4h/resources/sample_data/statewide_sample_data/IL_Statewide_Surface_Elev_ft.tif
wells4hydrogeology-0.2.1.dist-info/licenses/LICENSE
wells4hydrogeology-0.2.1.dist-info/METADATA
wells4hydrogeology-0.2.1.dist-info/WHEEL
wells4hydrogeology-0.2.1.dist-info/top_level.txt
wells4hydrogeology-0.2.1.dist-info/RECORD
