Metadata-Version: 2.4
Name: wells4hydrogeology
Version: 0.2.1
Summary: A package to read in geology data from wells and create a layered, gridded hydrogeologic model of a study region, all within a python environment, automating and performing tasks often carried out in a dedicated GIS software.
Author: Riley Balikian
Author-email: balikian@illinois.edu
License: MIT License
Project-URL: Homepage, https://github.com/RJbalikian/wells4hydrogeology
Project-URL: API Docs (Github Pages), https://rjbalikian.github.io/wells4hydrogeology/main.html
Project-URL: API Docs (ReadtheDocs), https://wells4hydrogeology.readthedocs.io/en/latest/
Project-URL: API Docs (dev - ReadtheDocs), https://wells4hydrogeology.readthedocs.io/en/dev/
Project-URL: Tutorials & Wiki, https://github.com/RJbalikian/wells4hydrogeology/wiki
Keywords: hydrogeology,modflow,water wells,geology,water,geotechnical
Classifier: Programming Language :: Python :: 3
Classifier: Intended Audience :: Science/Research
Classifier: License :: OSI Approved :: MIT License
Classifier: Operating System :: OS Independent
Requires-Python: <3.13,>=3.9
License-File: LICENSE
Requires-Dist: geopandas
Requires-Dist: rioxarray
Requires-Dist: owslib
Requires-Dist: scipy
Requires-Dist: matplotlib
Requires-Dist: pandas
Requires-Dist: numpy
Requires-Dist: dask
Requires-Dist: setuptools
Dynamic: author
Dynamic: author-email
Dynamic: description
Dynamic: description-content-type
Dynamic: license-file
